sid2re/__init__.py
sid2re/benchmarks.py
sid2re/driftgenerator/__init__.py
sid2re/driftgenerator/concept/__init__.py
sid2re/driftgenerator/concept/drift_behaviours/__init__.py
sid2re/driftgenerator/concept/drift_behaviours/base_drift_behaviour.py
sid2re/driftgenerator/concept/drift_behaviours/faulty_sensor_drift_behaviour.py
sid2re/driftgenerator/concept/drift_behaviours/gradual_drift_behaviour.py
sid2re/driftgenerator/concept/drift_behaviours/incremental_drift_behaviour.py
sid2re/driftgenerator/concept/drift_behaviours/sudden_drift_behaviour.py
sid2re/driftgenerator/concept/drift_transition_functions/__init__.py
sid2re/driftgenerator/concept/drift_transition_functions/base_transition_function.py
sid2re/driftgenerator/concept/drift_transition_functions/linear_transition_function.py
sid2re/driftgenerator/concept/graph_concept.py
sid2re/driftgenerator/concept/nodes/__init__.py
sid2re/driftgenerator/concept/nodes/base_node.py
sid2re/driftgenerator/concept/nodes/concept_node.py
sid2re/driftgenerator/concept/nodes/function_feature_node.py
sid2re/driftgenerator/concept/nodes/root_distributions/__init__.py
sid2re/driftgenerator/concept/nodes/root_distributions/base_distribution.py
sid2re/driftgenerator/concept/nodes/root_distributions/constant_distribution.py
sid2re/driftgenerator/concept/nodes/root_distributions/gaussian_distribution.py
sid2re/driftgenerator/concept/nodes/root_distributions/periodical_distribution.py
sid2re/driftgenerator/concept/nodes/root_distributions/uniform_distribution.py
sid2re/driftgenerator/concept/nodes/root_feature_node.py
sid2re/driftgenerator/concept/utils.py
sid2re/driftgenerator/generator.py
sid2re/driftgenerator/utils/__init__.py
sid2re/driftgenerator/utils/files.py
sid2re/driftgenerator/utils/metrics.py
sid2re/driftgenerator/utils/type_aliases.py
sid2re/py.typed
sid2regenerator-0.3.0.dist-info/LICENSE.txt
sid2regenerator-0.3.0.dist-info/METADATA
sid2regenerator-0.3.0.dist-info/WHEEL
sid2regenerator-0.3.0.dist-info/entry_points.txt
sid2regenerator-0.3.0.dist-info/RECORD
