Metadata-Version: 2.1
Name: SiD2ReGenerator
Version: 0.3.0
Summary: The SiD2ReGenerator Python project
Home-page: https://github.com/FraunhoferIOSB/SiD2Re
License: BSD-3-Clause
Keywords: tool,ml
Author: B. Stratmann
Author-email: benedikt.stratmann@iosb.fraunhofer.de
Maintainer: B. Stratmann
Maintainer-email: benedikt.stratmann@iosb.fraunhofer.de
Requires-Python: >=3.10,<3.12
Classifier: License :: OSI Approved :: BSD License
Classifier: Operating System :: OS Independent
Classifier: Programming Language :: Python :: 3
Classifier: Programming Language :: Python :: 3.10
Classifier: Programming Language :: Python :: 3.11
Classifier: Programming Language :: Python :: 3 :: Only
Classifier: Programming Language :: Python :: 3.8
Classifier: Programming Language :: Python :: 3.9
Requires-Dist: matplotlib (>=3.6.3,<4.0.0)
Requires-Dist: networkx (>=3.1,<4.0)
Requires-Dist: numpy (>=1.24.1,<2.0.0)
Requires-Dist: pandas
Requires-Dist: pyyaml
Requires-Dist: scikit-learn (>=1.2.1,<2.0.0)
Requires-Dist: seaborn (>=0.12.2,<0.13.0)
Requires-Dist: tqdm
Project-URL: Repository, https://github.com/FraunhoferIOSB/SiD2Re
